ogr2pbf/__init__.py
ogr2pbf/__main__.py
ogr2pbf/datawriter_base_class.py
ogr2pbf/fileformat_pb2.py
ogr2pbf/ogr2pbf.py
ogr2pbf/ogr_datasource.py
ogr2pbf/osm_data.py
ogr2pbf/osm_datawriter.py
ogr2pbf/osm_geometries.py
ogr2pbf/osmformat_pb2.py
ogr2pbf/pbf_datawriter.py
ogr2pbf/translation_base_class.py
ogr2pbf/version.py
ogr2pbf-0.1.2.dist-info/LICENSE
ogr2pbf-0.1.2.dist-info/METADATA
ogr2pbf-0.1.2.dist-info/WHEEL
ogr2pbf-0.1.2.dist-info/entry_points.txt
ogr2pbf-0.1.2.dist-info/top_level.txt
ogr2pbf-0.1.2.dist-info/RECORD
