Metadata-Version: 2.1
Name: ogr2pbf
Version: 0.1.2
Summary: A tool for converting ogr-readable files like shapefiles into .osm or .pbf data
Home-page: https://github.com/roelderickx/ogr2pbf
Author: Roel Derickx
Author-email: ogr2pbf.pypi@derickx.be
License: MIT License
Platform: UNKNOWN
Classifier: Environment :: Console
Classifier: Topic :: Scientific/Engineering :: GIS
Classifier: Development Status :: 5 - Production/Stable
Classifier: Programming Language :: Python :: 3
Classifier: License :: OSI Approved :: MIT License
Classifier: Operating System :: OS Independent
Requires-Python: >=3.7
